AUTHORS
HISTORY
LICENSE
MANIFEST.in
README.md
setup.cfg
setup.py
cinemaflix/__init__.py
cinemaflix/cli.py
cinemaflix/config.ini
cinemaflix/main.py
cinemaflix.egg-info/PKG-INFO
cinemaflix.egg-info/SOURCES.txt
cinemaflix.egg-info/dependency_links.txt
cinemaflix.egg-info/entry_points.txt
cinemaflix.egg-info/pbr.json
cinemaflix.egg-info/requires.txt
cinemaflix.egg-info/top_level.txt
cinemaflix/providers/__init__.py
cinemaflix/providers/constants.py
cinemaflix/providers/cpasbien.py
cinemaflix/providers/eztv.py
cinemaflix/providers/kickass.py
cinemaflix/providers/models.py
cinemaflix/providers/nyaa.py
cinemaflix/providers/provider.py
cinemaflix/providers/rarbg.py
cinemaflix/providers/rarbgapi.py
cinemaflix/providers/searchapi.py
cinemaflix/providers/tpb.py
cinemaflix/providers/yts.py
cinemaflix/utils/__init__.py
cinemaflix/utils/handler.py
tests/__init__.py