Metadata-Version: 1.1
Name: cinemaflix
Version: 3.0.0
Summary: A command line tool  to find and play movies online
Home-page: https://github.com/walidsa3d/cinemaflix
Author: Walid Saad
Author-email: walid.sa3d@gmail.com
License: MIT
Keywords: cli torrent movies
Platform: UNKNOWN
Classifier: Development Status :: 4 - Beta
Classifier: Environment :: Console
Classifier: Intended Audience :: End Users/Desktop
Classifier: License :: OSI Approved :: MIT License
Classifier: Operating System :: OS Independent
Classifier: Natural Language :: English
Classifier: Operating System :: OS Independent
Classifier: Programming Language :: Python :: 2
Classifier: Topic :: Multimedia :: Video
Classifier: Topic :: Utilities
